{"inkVersion":20,"root":[["^While the ship takes a short breather you peruse some of the non-urgent messages and come across an intriguing advertisement. It asks that anyone willing to donate do so in order to fund an experimental project. If enough money is raised it will increase the rewards funders receive. Shall you donate to the cause?","\n","ev","str","^Donate a large amount","/str","/ev",{"*":"0.c-0","flg":4},{"c-0":[{"->":"Larg"},"\n",{"->":"0.g-0"},{"#f":5}],"g-0":["done",{"#f":5}]}],"done",{"Larg":[["^You contribute a hefty chunk of change to the project , the results of which you receive promptly.","\n","ev","str","^Proceed","/str","/ev",{"*":".^.c-0","flg":4},"ev","str","^Donate a small amount","/str","/ev",{"*":".^.c-1","flg":4},{"c-0":["\n",["ev","visit",6,"seq","/ev","ev","du",0,"==","/ev",{"->":".^.s0","c":true},"ev","du",1,"==","/ev",{"->":".^.s1","c":true},"ev","du",2,"==","/ev",{"->":".^.s2","c":true},"ev","du",3,"==","/ev",{"->":".^.s3","c":true},"ev","du",4,"==","/ev",{"->":".^.s4","c":true},"ev","du",5,"==","/ev",{"->":".^.s5","c":true},"nop",{"s0":["pop","\n",{"->":"IMP"},{"->":".^.^.41"},null],"s1":["pop","\n",{"->":"SHM"},{"->":".^.^.41"},null],"s2":["pop","\n",{"->":"Drone"},{"->":".^.^.41"},null],"s3":["pop","\n",{"->":"Drink"},{"->":".^.^.41"},null],"s4":["pop","\n",{"->":"Irri"},{"->":".^.^.41"},null],"s5":["pop","\n",{"->":"Scam"},{"->":".^.^.41"},null],"#f":5}],"\n",{"#f":5}],"c-1":[{"->":"Smol"},"\n",{"#f":5}]}],{"#f":1}],"Smol":[["^You provide a small amount of credits to the project, and receive the results rather quickly.","\n","ev","str","^Proceed","/str","/ev",{"*":".^.c-0","flg":4},"ev","str","^Ignore the Ad","/str","/ev",{"*":".^.c-1","flg":4},{"c-0":["\n",["ev","visit",4,"seq","/ev","ev","du",0,"==","/ev",{"->":".^.s0","c":true},"ev","du",1,"==","/ev",{"->":".^.s1","c":true},"ev","du",2,"==","/ev",{"->":".^.s2","c":true},"ev","du",3,"==","/ev",{"->":".^.s3","c":true},"nop",{"s0":["pop","\n",{"->":"Drone"},{"->":".^.^.29"},null],"s1":["pop","\n",{"->":"Drink"},{"->":".^.^.29"},null],"s2":["pop","\n",{"->":"Irri"},{"->":".^.^.29"},null],"s3":["pop","\n",{"->":"Scam"},{"->":".^.^.29"},null],"#f":5}],"\n",{"#f":5}],"c-1":[{"->":"Ignore"},"\n",{"#f":5}]}],{"#f":1}],"IMP":["^You’re rewarded with Improved Power Cells, they can hold even more energy.","\n","done",{"#f":1}],"SHM":["^You receive instructions on how to improve your hull durability. They prove incredibly effective, further strengthening the hull.","\n","done",{"#f":1}],"Drone":["^Your donation is rewarded with a pleasant little Security Drone. It will monitor the ship corridors alongside the regular detail.","\n","done",{"#f":1}],"Drink":["^The revolutionary product your donation helped to fund is a drink machine that never needs to be refilled. The crew are pleased after the machine is installed in the mess hall and thank you for the addition to the ship.","\n","done",{"#f":1}],"Irri":["^Your compensation comes in the form of a recipe for improved irrigation. After some tweaks to hydroponics it yields wonderful results.","\n","done",{"#f":1}],"Scam":["^You get nothing. After the credits leave your account so too does the message asking for donations. It appears you’ve been had. Best keep an eye out for something like this in the future.","\n","done",{"#f":1}],"Ignore":["^You promptly ignore the advertisement and continue on with the journey at hand, content in the credits you’ve managed to keep.","\n","done",{"#f":1}],"#f":1}],"listDefs":{}}